agentslib/__init__.py
agentslib/app.py
agentslib/config_loader.py
agentslib/config/agent.json
agentslib/config/prompts.yaml
agentslib/tools/__init__.py
agentslib/tools/git_silent_clone.py
agentslib/tools/unibox_tools.py
agentslib/tools/_default/__init__.py
agentslib/tools/_default/final_answer.py
agentslib/tools/_default/visit_webpage.py
agentslib/tools/_default/web_search.py
agentslib/ui/Gradio_UI.py
agentslib-0.1.0.dist-info/METADATA
agentslib-0.1.0.dist-info/WHEEL
agentslib-0.1.0.dist-info/entry_points.txt
agentslib-0.1.0.dist-info/licenses/LICENSE
agentslib-0.1.0.dist-info/RECORD
