Metadata-Version: 2.4
Name: agentslib
Version: 0.1.0
Summary: Add your description here
Author-email: yada <trojblue@gmail.com>
License-File: LICENSE
Requires-Python: >=3.10
Requires-Dist: duckduckgo-search>=7.5.5
Requires-Dist: pytz>=2025.2
Requires-Dist: requests>=2.32.3
Requires-Dist: smolagents>=1.12.0
